setup.py
antstar/Ant.py
antstar/AntBrain.py
antstar/AntFeeler.py
antstar/ByPassAntBrain.py
antstar/DirectionByPassAntBrain.py
antstar/GlueWallAntBrain.py
antstar/Grid.py
antstar/__init__.py
antstar/exceptions.py
antstar/geometry.py
antstar.egg-info/PKG-INFO
antstar.egg-info/SOURCES.txt
antstar.egg-info/dependency_links.txt
antstar.egg-info/top_level.txt